dcFBA/DefaultModels.py
dcFBA/Exceptions.py
dcFBA/__init__.py
dcFBA/DynamicModels/DynamicFBABase.py
dcFBA/DynamicModels/DynamicJointFBA.py
dcFBA/DynamicModels/DynamicModelBase.py
dcFBA/DynamicModels/DynamicParallelFBA.py
dcFBA/DynamicModels/DynamicSingleFBA.py
dcFBA/DynamicModels/EndPointFBA.py
dcFBA/DynamicModels/StaticOptimizationModel.py
dcFBA/DynamicModels/__init__.py
dcFBA/Helpers/BuildCommunityMatrix.py
dcFBA/Helpers/BuildEndPointModel.py
dcFBA/Helpers/KineticsReaderInterface.py
dcFBA/Helpers/OptimalSearch.py
dcFBA/Helpers/ReduceModel.py
dcFBA/Helpers/__init__.py
dcFBA/Models/CommunityModel.py
dcFBA/Models/KineticsStruct.py
dcFBA/Models/Transporters.py
dcFBA/Models/__init__.py
dcFBA/ToyModels/__init__.py
dcFBA/ToyModels/combined_model.py
dcFBA/ToyModels/model_a.py
dcFBA/ToyModels/model_b.py
dcFBA/ToyModels/model_c.py
dcFBA/ToyModels/model_d.py
dcFBA/ToyModels/Examples/DJFBA_example.py
dcFBA/ToyModels/Examples/DynamicSingle_example.py
dcFBA/ToyModels/Examples/EndPointFBA_example.py
dcFBA/ToyModels/Examples/Parallel_example.py
dcFBA/ToyModels/Examples/epFBA_QP_example.py
dcFBA/ToyModels/Examples/strep_test.py
dcFBA-0.1.2.dist-info/LICENSE
dcFBA-0.1.2.dist-info/METADATA
dcFBA-0.1.2.dist-info/WHEEL
dcFBA-0.1.2.dist-info/top_level.txt
dcFBA-0.1.2.dist-info/RECORD
