Metadata-Version: 2.1
Name: dcFBA
Version: 0.1.2
Summary: Python package for Dynamic Community FBA
Home-page: https://github.com/SystemsBioinformatics/dynamic-community-fba
Author: Steven Wijnen, Francesco Moro, Brett Olivier
Author-email: Steven Wijnen <steven.wijnen@icloud.com>, Francesco Moro <f.moro@vu.nl>, Brett Olivier <b.g.olivier@vu.nl>
License: MIT License
Project-URL: homepage, https://github.com/SystemsBioinformatics/dynamic-community-fba
Project-URL: bug-tracker, https://github.com/SystemsBioinformatics/dynamic-community-fba/issues
Project-URL: docs, https://dynamic-community-fba.readthedocs.io/en/latest/index.html
Keywords: Microbial Community,Systems Biology,Dynamic FBA,Genome Scale Models
Classifier: Programming Language :: Python :: 3
Classifier: Operating System :: OS Independent
Requires-Python: <3.11,>=3.8
License-File: LICENSE
Requires-Dist: cbmpy >=0.8.8
Requires-Dist: pyparsing >=3.0
